apa102_pi/__init__.py
apa102_pi/colorschemes/__init__.py
apa102_pi/colorschemes/colorschemes.py
apa102_pi/driver/__init__.py
apa102_pi/driver/apa102.py
apa102_pi/driver/colorcycletemplate.py
apa102_pi/driver/test_apa102.py
apa102_pi-2.5.2.dist-info/LICENSE
apa102_pi-2.5.2.dist-info/METADATA
apa102_pi-2.5.2.dist-info/WHEEL
apa102_pi-2.5.2.dist-info/top_level.txt
apa102_pi-2.5.2.dist-info/RECORD
