Metadata-Version: 2.1
Name: apa102-pi
Version: 2.5.2
Summary: Driver for APA102 LEDs on a Raspberry Pi
Author-email: Martin Erzberger <martin@erzberger.ch>
Project-URL: Homepage, https://github.com/tinue/apa102-pi
Project-URL: Issues, https://github.com/tinue/apa102-pi/issues
Keywords: apa102,led,SK9822,superled,dotstar,raspberry pi
Classifier: Programming Language :: Python :: 3
Classifier: License :: OSI Approved :: GNU General Public License v3 (GPLv3)
Classifier: Intended Audience :: Education
Classifier: Operating System :: POSIX :: Linux
Classifier: Topic :: Education
Classifier: Topic :: System :: Hardware :: Hardware Drivers
Classifier: Topic :: Software Development :: Libraries :: Python Modules
Requires-Python: >3
License-File: LICENSE
Requires-Dist: adafruit-circuitpython-bitbangio
Requires-Dist: adafruit-circuitpython-busdevice
